sliders/__init__.py
sliders/__main__.py
sliders/cmd.py
sliders/settings.py
sliders_themad-0.0.1.dist-info/LICENSE.txt
sliders_themad-0.0.1.dist-info/METADATA
sliders_themad-0.0.1.dist-info/WHEEL
sliders_themad-0.0.1.dist-info/top_level.txt
sliders_themad-0.0.1.dist-info/RECORD
