Metadata-Version: 2.1
Name: sliders-themad
Version: 0.0.1
Summary: Non-GUI IDE for Python.
Author-email: Themadpunter <themadpunter10@gmail.cpm>
Requires-Python: >3.5
License-File: LICENSE.txt
